line_notify_helper/__init__.py
line_notify_helper/line_notify.py
linenotifyhelper-0.0.1.dist-info/METADATA
linenotifyhelper-0.0.1.dist-info/WHEEL
linenotifyhelper-0.0.1.dist-info/top_level.txt
linenotifyhelper-0.0.1.dist-info/RECORD
