Metadata-Version: 2.1
Name: linenotifyhelper
Version: 0.0.1
Summary: A small test project through which program messages can be sent back and forth to the line
Home-page: https://github.com/tzamou/line_notify_helper
Author: Guan-Lin Chen
Author-email: ken54787845@gmail.com
Classifier: Programming Language :: Python :: 3
Classifier: License :: OSI Approved :: MIT License
Classifier: Operating System :: OS Independent
Requires-Python: >=3.6
